monitor/modules/__init__.py
monitor/modules/filecheck.py
monitor/modules/logs.py
monitor/modules/suppress.py
monitor/modules/test_filecheck.py
monitor_py-0.1.2.data/scripts/scan.py
monitor_py-0.1.2.dist-info/LICENSE
monitor_py-0.1.2.dist-info/METADATA
monitor_py-0.1.2.dist-info/WHEEL
monitor_py-0.1.2.dist-info/top_level.txt
monitor_py-0.1.2.dist-info/RECORD
