Metadata-Version: 2.1
Name: monitor-py
Version: 0.1.2
Summary: Package to monitor if servers are available to connect
Home-page: https://github.com/bboykin87/monitor.py
Author: Brandon Boykin
Author-email: bboykin87@gmail.com
License: UNKNOWN
Platform: UNKNOWN
Classifier: Programming Language :: Python :: 3
Classifier: Operating System :: POSIX :: Linux
Requires-Python: >=3.6
